LICENSE.txt
MANIFEST.in
README.rst
setup.py
django_autoslug/__init__.py
django_autoslug/fields.py
django_autoslug_field.egg-info/PKG-INFO
django_autoslug_field.egg-info/SOURCES.txt
django_autoslug_field.egg-info/dependency_links.txt
django_autoslug_field.egg-info/top_level.txt
testautoslug/__init__.py
testautoslug/manage.py
testautoslug/settings.py
testautoslug/urls.py
testautoslug/testapp/__init__.py
testautoslug/testapp/admin.py
testautoslug/testapp/models.py
testautoslug/testapp/tests.py
testautoslug/testapp/views.py