Metadata-Version: 1.0
Name: django-autoslug-field
Version: 0.2.2
Summary: AutoSlugField for Django based on django-extensions AutoSlugField, adds option to track foreignkey/parent field for slug.
Home-page: http://github.com/aljosa/django-autoslug-field/
Author: Aljosa Mohorovic
Author-email: aljosa.mohorovic@gmail.com
License: MIT License
Keywords: django autoslug slug field
Platform: any
